LICENSE
MANIFEST.in
README.rst
setup.py
rookout/__init__.py
rookout/base.py
rookout/conf.py
rookout/ftp.py
rookout/gettext.py
rookout/git.py
rookout/lua.py
rookout.egg-info/PKG-INFO
rookout.egg-info/SOURCES.txt
rookout.egg-info/dependency_links.txt
rookout.egg-info/top_level.txt