Metadata-Version: 1.1
Name: rookout
Version: 0.4.8
Summary: A rookie's workout library by zrong.
Home-page: http://github.com/zrong/rookout
Author: zrong
Author-email: zrongzrong@gmail.com
License: MIT
Keywords: utils development zrong rookie workout
Platform: UNKNOWN
Classifier: Programming Language :: Python :: 3
Classifier: Development Status :: 4 - Beta
Classifier: License :: OSI Approved :: MIT License
Classifier: Operating System :: OS Independent
Classifier: Topic :: Software Development :: Libraries :: Python Modules
